.gitignore
.readthedocs.yaml
LICENSE.md
MANIFEST.in
README.md
setup.cfg
setup.py
docs/Makefile
docs/make.bat
docs/requirements.txt
docs/build/doctrees/editing_effect.doctree
docs/build/doctrees/environment.pickle
docs/build/doctrees/gRNA_mutation.doctree
docs/build/doctrees/index.doctree
docs/build/doctrees/installation.doctree
docs/build/doctrees/introduction.doctree
docs/build/doctrees/output.doctree
docs/build/html/.buildinfo
docs/build/html/editing_effect.html
docs/build/html/gRNA_mutation.html
docs/build/html/genindex.html
docs/build/html/index.html
docs/build/html/installation.html
docs/build/html/introduction.html
docs/build/html/objects.inv
docs/build/html/output.html
docs/build/html/search.html
docs/build/html/searchindex.js
docs/build/html/_images/scheme.png
docs/build/html/_sources/editing_effect.rst.txt
docs/build/html/_sources/gRNA_mutation.rst.txt
docs/build/html/_sources/index.rst.txt
docs/build/html/_sources/installation.rst.txt
docs/build/html/_sources/introduction.rst.txt
docs/build/html/_sources/output.rst.txt
docs/build/html/_static/_sphinx_javascript_frameworks_compat.js
docs/build/html/_static/basic.css
docs/build/html/_static/doctools.js
docs/build/html/_static/documentation_options.js
docs/build/html/_static/file.png
docs/build/html/_static/jquery-3.6.0.js
docs/build/html/_static/jquery.js
docs/build/html/_static/language_data.js
docs/build/html/_static/minus.png
docs/build/html/_static/plus.png
docs/build/html/_static/pygments.css
docs/build/html/_static/searchtools.js
docs/build/html/_static/sphinx_highlight.js
docs/build/html/_static/underscore-1.13.1.js
docs/build/html/_static/underscore.js
docs/build/html/_static/css/badge_only.css
docs/build/html/_static/css/theme.css
docs/build/html/_static/css/fonts/Roboto-Slab-Bold.woff
docs/build/html/_static/css/fonts/Roboto-Slab-Bold.woff2
docs/build/html/_static/css/fonts/Roboto-Slab-Regular.woff
docs/build/html/_static/css/fonts/Roboto-Slab-Regular.woff2
girafr.egg-info/PKG-INFO
girafr.egg-info/SOURCES.txt
girafr.egg-info/dependency_links.txt
girafr.egg-info/entry_points.txt
girafr.egg-info/requires.txt
girafr.egg-info/top_level.txt