Metadata-Version: 2.1
Name: girafr
Version: 1.1.0
Summary: A package to detect mutations and CRISPR-Cas9 editing effects in single cell CRISPR screens
Home-page: https://github.com/FunctionalEpigeneticsLab/GiRAFR
Author: Laboratory for Functional Epigentics, KU Leuven
Author-email: qian.yu@kuleuven.be
Project-URL: Bug Reports, https://github.com/FunctionalEpigeneticsLab/GiRAFR/issues
Project-URL: Source, https://github.com/FunctionalEpigeneticsLab/GiRAFR
Keywords: gRNA,mutation,single cell CRISPR screen
Classifier: Development Status :: 3 - Alpha
Classifier: Topic :: Scientific/Engineering :: Bio-Informatics
Classifier: License :: OSI Approved :: MIT License
Classifier: Programming Language :: Python :: 3
Classifier: Programming Language :: Python :: 3.7
Classifier: Programming Language :: Python :: 3.8
Classifier: Programming Language :: Python :: 3.9
Classifier: Programming Language :: Python :: 3.10
Classifier: Programming Language :: Python :: 3 :: Only
Requires-Python: >=3.7, <4
License-File: LICENSE.md
